rusty_py_core-0.1.1.dist-info/METADATA
rusty_py_core-0.1.1.dist-info/WHEEL
rusty_py/core/rust_lib.pyi
rusty_py/core/__init__.py
rusty_py/core/py.typed
rusty_py/core/rust_lib.cpython-310-darwin.so
rusty_py_core-0.1.1.dist-info/RECORD
